lib/logical/all.v
`include "and.v"
`include "buff.v"
`include "dff.v"
`include "jtl.v"
`include "merge.v"
`include "ndro.sv"
`include "not.v"
`include "or.v"
`include "split.v"
`include "xnor.v"
`include "xor.v"
`include "zero_async.v"

lib/logical/merge.v
module rustsfq_merge (
    input  wire a,
    input  wire b,
    output wire q,
    input  wire __cycle
);
  assign q = a | b;
endmodule

lib/logical/xor.v
module rustsfq_xor (
    input  wire a,
    input  wire b,
    input  wire clk,
    output wire q,
    input  wire __cycle
);
  reg a_reg = 1'b0, b_reg = 1'b0;

  assign q = clk ? (a | a_reg) ^ (b | b_reg) : 1'b0;

  always @(posedge __cycle) begin
    if (clk) begin
      a_reg <= 1'b0;
      b_reg <= 1'b0;
    end else begin
      a_reg <= a | a_reg;
      b_reg <= b | b_reg;
    end
  end
endmodule

lib/logical/and.v
module rustsfq_and (
    input  wire a,
    input  wire b,
    input  wire clk,
    output wire q,
    input  wire __cycle
);
  reg a_reg = 1'b0, b_reg = 1'b0;
  assign q = clk ? (a | a_reg) & (b | b_reg) : 1'b0;

  always @(posedge __cycle) begin
    if (clk) begin
      a_reg <= 1'b0;
      b_reg <= 1'b0;
    end else begin
      a_reg <= a | a_reg;
      b_reg <= b | b_reg;
    end
  end
endmodule

lib/logical/split.v
module rustsfq_split (
    input  wire a,
    output wire q1,
    output wire q2,
    input  wire __cycle
);
  assign q1 = a;
  assign q2 = a;
endmodule

samples/fulladder/logical/modules.v
module HalfAdder (a, b, clk, c, s, __cycle);
input a, b, clk, __cycle;
output c, s;
wire _SPLIT1_q1, _SPLIT1_q2, _SPLIT2_q1, _SPLIT2_q2, _SPLIT3_q1, _SPLIT3_q2;
reg _SPLIT2_q1_d1 = 1'b0, _SPLIT2_q2_d1 = 1'b0, _SPLIT3_q1_d1 = 1'b0, _SPLIT3_q2_d1 = 1'b0;
rustsfq_split SPLIT1 (clk, _SPLIT1_q1, _SPLIT1_q2, __cycle);
rustsfq_split SPLIT2 (a, _SPLIT2_q1, _SPLIT2_q2, __cycle);
rustsfq_split SPLIT3 (b, _SPLIT3_q1, _SPLIT3_q2, __cycle);
rustsfq_and AND4 (_SPLIT2_q1_d1, _SPLIT3_q1_d1, _SPLIT1_q1, c, __cycle);
rustsfq_xor XOR5 (_SPLIT2_q2_d1, _SPLIT3_q2_d1, _SPLIT1_q2, s, __cycle);
always @(posedge __cycle) begin
_SPLIT2_q2_d1 <= _SPLIT2_q2; _SPLIT3_q2_d1 <= _SPLIT3_q2; _SPLIT3_q1_d1 <= _SPLIT3_q1; _SPLIT2_q1_d1 <= _SPLIT2_q1;
end
endmodule
module FullAdder (a, b, cin, clk, cout, s, __cycle);
input a, b, cin, clk, __cycle;
output cout, s;
wire _BUFF10_q, _BUFF11_q, _BUFF12_q, _BUFF6_q, _BUFF7_q, _BUFF9_q, _DFF4_q, _DFF8_q, _HalfAdder13_c, _HalfAdder3_c, _HalfAdder3_s, _SPLIT1_q1, _SPLIT1_q2, _SPLIT2_q1, _SPLIT2_q2, _SPLIT5_q1, _SPLIT5_q2;
reg _BUFF7_q_d1 = 1'b0, cin_d1 = 1'b0;
rustsfq_split SPLIT1 (clk, _SPLIT1_q1, _SPLIT1_q2, __cycle);
rustsfq_split SPLIT2 (_SPLIT1_q1, _SPLIT2_q1, _SPLIT2_q2, __cycle);
HalfAdder HalfAdder3 (a, b, _SPLIT1_q2, _HalfAdder3_c, _HalfAdder3_s, __cycle);
rustsfq_dff DFF4 (cin_d1, _SPLIT2_q2, _DFF4_q, __cycle);
rustsfq_split SPLIT5 (_SPLIT2_q1, _SPLIT5_q1, _SPLIT5_q2, __cycle);
rustsfq_buff BUFF6 (_HalfAdder3_c, _BUFF6_q, __cycle);
rustsfq_buff BUFF7 (_BUFF6_q, _BUFF7_q, __cycle);
rustsfq_dff DFF8 (_BUFF7_q_d1, _SPLIT5_q1, _DFF8_q, __cycle);
rustsfq_buff BUFF9 (_HalfAdder3_s, _BUFF9_q, __cycle);
rustsfq_buff BUFF10 (_BUFF9_q, _BUFF10_q, __cycle);
rustsfq_buff BUFF11 (_DFF4_q, _BUFF11_q, __cycle);
rustsfq_buff BUFF12 (_BUFF11_q, _BUFF12_q, __cycle);
HalfAdder HalfAdder13 (_BUFF10_q, _BUFF12_q, _SPLIT5_q2, _HalfAdder13_c, s, __cycle);
rustsfq_merge MERGE14 (_DFF8_q, _HalfAdder13_c, cout, __cycle);
always @(posedge __cycle) begin
_BUFF7_q_d1 <= _BUFF7_q; cin_d1 <= cin;
end
endmodule

lib/logical/buff.v
module rustsfq_buff (
    input  wire a,
    output wire q,
    input  wire __cycle
);
  assign q = a;
endmodule

lib/logical/dff.v
module rustsfq_dff (
    input  wire a,
    input  wire clk,
    output wire q,
    input  wire __cycle
);
  reg a_reg = 1'b0;

  assign q = clk ? (a | a_reg) : 1'b0;

  always @(posedge __cycle) begin
    if (clk) begin
      a_reg <= 1'b0;
    end else begin
      a_reg <= a | a_reg;
    end
  end
endmodule

samples/fulladder/logical/fulladder.sv
`timescale 1ps / 100fs
`include "all.v"
`include "modules.v"

module top;
  // Inputs
  reg a, b, cin, clk;
  // Outputs
  wire cout, s;

  reg __cycle;
  integer step;

  FullAdder dut (.*);

  // Simulation Steps
  initial begin
    __cycle = 0;
    step = 0;
    forever begin
      #50;
      __cycle = 0;
      #50;
      __cycle = 1;
      step = step + 1;
    end
  end

  // Input patterns
  initial begin
    cin = 0;
    b = 0;
    a = 0;
    clk = 1;
    @(posedge __cycle);
    cin <= 0;
    b <= 0;
    a <= 1;
    clk <= 1;
    @(posedge __cycle);
    cin <= 0;
    b <= 1;
    a <= 0;
    clk <= 1;
    @(posedge __cycle);
    cin <= 0;
    b <= 1;
    a <= 1;
    clk <= 1;
    @(posedge __cycle);
    cin <= 1;
    b <= 0;
    a <= 0;
    clk <= 1;
    @(posedge __cycle);
    cin <= 1;
    b <= 0;
    a <= 1;
    clk <= 1;
    @(posedge __cycle);
    cin <= 1;
    b <= 1;
    a <= 0;
    clk <= 1;
    @(posedge __cycle);
    cin <= 1;
    b <= 1;
    a <= 1;
    clk <= 1;
    @(posedge __cycle);
    cin <= 0;
    b <= 0;
    a <= 0;
    clk <= 1;
    @(posedge __cycle);
    cin <= 0;
    b <= 0;
    a <= 0;
    clk <= 1;
    @(posedge __cycle);
    cin <= 0;
    b <= 0;
    a <= 0;
    clk <= 1;
    @(posedge __cycle);
    $finish;
  end

  initial begin
    $dumpfile("FullAdder.vcd");
    $dumpvars(0, top);
  end
endmodule

samples/fulladder/logical/FullAdder.vcd
$date
	Tue Jul  7 13:57:44 2026
$end
$version
	Icarus Verilog
$end
$timescale
	100fs
$end
$scope module top $end
$var wire 1 ! s $end
$var wire 1 " cout $end
$var reg 1 # __cycle $end
$var reg 1 $ a $end
$var reg 1 % b $end
$var reg 1 & cin $end
$var reg 1 ' clk $end
$var integer 32 ( step [31:0] $end
$scope module dut $end
$var wire 1 # __cycle $end
$var wire 1 $ a $end
$var wire 1 % b $end
$var wire 1 & cin $end
$var wire 1 ' clk $end
$var wire 1 ! s $end
$var wire 1 " cout $end
$var wire 1 ) _SPLIT5_q2 $end
$var wire 1 * _SPLIT5_q1 $end
$var wire 1 + _SPLIT2_q2 $end
$var wire 1 , _SPLIT2_q1 $end
$var wire 1 - _SPLIT1_q2 $end
$var wire 1 . _SPLIT1_q1 $end
$var wire 1 / _HalfAdder3_s $end
$var wire 1 0 _HalfAdder3_c $end
$var wire 1 1 _HalfAdder13_c $end
$var wire 1 2 _DFF8_q $end
$var wire 1 3 _DFF4_q $end
$var wire 1 4 _BUFF9_q $end
$var wire 1 5 _BUFF7_q $end
$var wire 1 6 _BUFF6_q $end
$var wire 1 7 _BUFF12_q $end
$var wire 1 8 _BUFF11_q $end
$var wire 1 9 _BUFF10_q $end
$var reg 1 : _BUFF7_q_d1 $end
$var reg 1 ; cin_d1 $end
$scope module BUFF10 $end
$var wire 1 # __cycle $end
$var wire 1 9 q $end
$var wire 1 4 a $end
$upscope $end
$scope module BUFF11 $end
$var wire 1 # __cycle $end
$var wire 1 8 q $end
$var wire 1 3 a $end
$upscope $end
$scope module BUFF12 $end
$var wire 1 # __cycle $end
$var wire 1 8 a $end
$var wire 1 7 q $end
$upscope $end
$scope module BUFF6 $end
$var wire 1 # __cycle $end
$var wire 1 6 q $end
$var wire 1 0 a $end
$upscope $end
$scope module BUFF7 $end
$var wire 1 # __cycle $end
$var wire 1 6 a $end
$var wire 1 5 q $end
$upscope $end
$scope module BUFF9 $end
$var wire 1 # __cycle $end
$var wire 1 4 q $end
$var wire 1 / a $end
$upscope $end
$scope module DFF4 $end
$var wire 1 # __cycle $end
$var wire 1 ; a $end
$var wire 1 3 q $end
$var wire 1 + clk $end
$var reg 1 < a_reg $end
$upscope $end
$scope module DFF8 $end
$var wire 1 # __cycle $end
$var wire 1 : a $end
$var wire 1 2 q $end
$var wire 1 * clk $end
$var reg 1 = a_reg $end
$upscope $end
$scope module HalfAdder13 $end
$var wire 1 # __cycle $end
$var wire 1 9 a $end
$var wire 1 7 b $end
$var wire 1 ! s $end
$var wire 1 ) clk $end
$var wire 1 1 c $end
$var wire 1 > _SPLIT3_q2 $end
$var wire 1 ? _SPLIT3_q1 $end
$var wire 1 @ _SPLIT2_q2 $end
$var wire 1 A _SPLIT2_q1 $end
$var wire 1 B _SPLIT1_q2 $end
$var wire 1 C _SPLIT1_q1 $end
$var reg 1 D _SPLIT2_q1_d1 $end
$var reg 1 E _SPLIT2_q2_d1 $end
$var reg 1 F _SPLIT3_q1_d1 $end
$var reg 1 G _SPLIT3_q2_d1 $end
$scope module AND4 $end
$var wire 1 # __cycle $end
$var wire 1 D a $end
$var wire 1 F b $end
$var wire 1 1 q $end
$var wire 1 C clk $end
$var reg 1 H a_reg $end
$var reg 1 I b_reg $end
$upscope $end
$scope module SPLIT1 $end
$var wire 1 # __cycle $end
$var wire 1 C q1 $end
$var wire 1 B q2 $end
$var wire 1 ) a $end
$upscope $end
$scope module SPLIT2 $end
$var wire 1 # __cycle $end
$var wire 1 9 a $end
$var wire 1 A q1 $end
$var wire 1 @ q2 $end
$upscope $end
$scope module SPLIT3 $end
$var wire 1 # __cycle $end
$var wire 1 7 a $end
$var wire 1 ? q1 $end
$var wire 1 > q2 $end
$upscope $end
$scope module XOR5 $end
$var wire 1 # __cycle $end
$var wire 1 E a $end
$var wire 1 G b $end
$var wire 1 B clk $end
$var wire 1 ! q $end
$var reg 1 J a_reg $end
$var reg 1 K b_reg $end
$upscope $end
$upscope $end
$scope module HalfAdder3 $end
$var wire 1 # __cycle $end
$var wire 1 $ a $end
$var wire 1 % b $end
$var wire 1 / s $end
$var wire 1 - clk $end
$var wire 1 0 c $end
$var wire 1 L _SPLIT3_q2 $end
$var wire 1 M _SPLIT3_q1 $end
$var wire 1 N _SPLIT2_q2 $end
$var wire 1 O _SPLIT2_q1 $end
$var wire 1 P _SPLIT1_q2 $end
$var wire 1 Q _SPLIT1_q1 $end
$var reg 1 R _SPLIT2_q1_d1 $end
$var reg 1 S _SPLIT2_q2_d1 $end
$var reg 1 T _SPLIT3_q1_d1 $end
$var reg 1 U _SPLIT3_q2_d1 $end
$scope module AND4 $end
$var wire 1 # __cycle $end
$var wire 1 R a $end
$var wire 1 T b $end
$var wire 1 0 q $end
$var wire 1 Q clk $end
$var reg 1 V a_reg $end
$var reg 1 W b_reg $end
$upscope $end
$scope module SPLIT1 $end
$var wire 1 # __cycle $end
$var wire 1 Q q1 $end
$var wire 1 P q2 $end
$var wire 1 - a $end
$upscope $end
$scope module SPLIT2 $end
$var wire 1 # __cycle $end
$var wire 1 $ a $end
$var wire 1 O q1 $end
$var wire 1 N q2 $end
$upscope $end
$scope module SPLIT3 $end
$var wire 1 # __cycle $end
$var wire 1 % a $end
$var wire 1 M q1 $end
$var wire 1 L q2 $end
$upscope $end
$scope module XOR5 $end
$var wire 1 # __cycle $end
$var wire 1 S a $end
$var wire 1 U b $end
$var wire 1 P clk $end
$var wire 1 / q $end
$var reg 1 X a_reg $end
$var reg 1 Y b_reg $end
$upscope $end
$upscope $end
$scope module MERGE14 $end
$var wire 1 # __cycle $end
$var wire 1 2 a $end
$var wire 1 1 b $end
$var wire 1 " q $end
$upscope $end
$scope module SPLIT1 $end
$var wire 1 # __cycle $end
$var wire 1 ' a $end
$var wire 1 . q1 $end
$var wire 1 - q2 $end
$upscope $end
$scope module SPLIT2 $end
$var wire 1 # __cycle $end
$var wire 1 . a $end
$var wire 1 , q1 $end
$var wire 1 + q2 $end
$upscope $end
$scope module SPLIT5 $end
$var wire 1 # __cycle $end
$var wire 1 , a $end
$var wire 1 * q1 $end
$var wire 1 ) q2 $end
$upscope $end
$upscope $end
$upscope $end
$enddefinitions $end
$comment Show the parameter values. $end
$dumpall
$end
#0
$dumpvars
0Y
0X
0W
0V
0U
0T
0S
0R
1Q
1P
0O
0N
0M
0L
0K
0J
0I
0H
0G
0F
0E
0D
1C
1B
0A
0@
0?
0>
0=
0<
0;
0:
09
08
07
06
05
04
03
02
01
00
0/
1.
1-
1,
1+
1*
1)
b0 (
1'
0&
0%
0$
0#
0"
0!
$end
#1000
1O
1N
1$
b1 (
1#
#1500
0#
#2000
1A
1@
19
14
1/
0O
0N
0$
1M
1L
1%
1R
1S
b10 (
1#
#2500
0#
#3000
1!
0R
1T
1U
0S
1D
1E
1O
1N
1$
b11 (
1#
#3500
0#
#4000
15
16
10
0A
0@
09
04
0/
0O
0N
0$
0M
0L
0%
1&
1R
1S
b100 (
1#
#4500
0#
#5000
05
06
00
0!
1"
1?
1>
17
18
13
12
0R
0T
0U
0S
0D
0E
1;
1:
1O
1N
1$
b101 (
1#
#5500
0#
#6000
0"
1!
1A
1@
19
14
1/
02
0O
0N
0$
1M
1L
1%
0:
1F
1G
1R
1S
b110 (
1#
#6500
0#
#7000
1"
11
0!
0R
1T
1U
0S
1D
1E
1O
1N
1$
b111 (
1#
#7500
0#
#8000
15
16
10
0A
0@
09
04
0/
0O
0N
0$
0M
0L
0%
0&
1R
1S
b1000 (
1#
#8500
0#
#9000
05
06
00
01
1!
0?
0>
07
08
03
12
0R
0T
0U
0S
0D
0E
0;
1:
b1001 (
1#
#9500
0#
#10000
0"
0!
02
0:
0F
0G
b1010 (
1#
#10500
0#
#11000
b1011 (
1#
