lib/logical/all.v
`include "and.v"
`include "buff.v"
`include "dff.v"
`include "jtl.v"
`include "merge.v"
`include "ndro.sv"
`include "not.v"
`include "or.v"
`include "split.v"
`include "xnor.v"
`include "xor.v"
`include "zero_async.v"

lib/logical/split.v
module rustsfq_split (
    input  wire a,
    output wire q1,
    output wire q2,
    input  wire __cycle
);
  assign q1 = a;
  assign q2 = a;
endmodule

lib/logical/or.v
module rustsfq_or (
    input  wire a,
    input  wire b,
    input  wire clk,
    output wire q,
    input  wire __cycle
);
  reg a_reg = 1'b0, b_reg = 1'b0;

  assign q = clk ? (a | a_reg) | (b | b_reg) : 1'b0;

  always @(posedge __cycle) begin
    if (clk) begin
      a_reg <= 1'b0;
      b_reg <= 1'b0;
    end else begin
      a_reg <= a | a_reg;
      b_reg <= b | b_reg;
    end
  end
endmodule

lib/logical/buff.v
module rustsfq_buff (
    input  wire a,
    output wire q,
    input  wire __cycle
);
  assign q = a;
endmodule

lib/logical/and.v
module rustsfq_and (
    input  wire a,
    input  wire b,
    input  wire clk,
    output wire q,
    input  wire __cycle
);
  reg a_reg = 1'b0, b_reg = 1'b0;
  assign q = clk ? (a | a_reg) & (b | b_reg) : 1'b0;

  always @(posedge __cycle) begin
    if (clk) begin
      a_reg <= 1'b0;
      b_reg <= 1'b0;
    end else begin
      a_reg <= a | a_reg;
      b_reg <= b | b_reg;
    end
  end
endmodule

samples/timings/logical/modules.v
module NorPipelined (a, b, clk, y, __cycle);
input a, b, clk, __cycle;
output y;
wire clk1, clk2, x;
reg a_d1 = 1'b0, b_d1 = 1'b0, x_d1 = 1'b0;
rustsfq_split SPLIT1 (clk, clk1, clk2, __cycle);
rustsfq_or OR2 (a_d1, b_d1, clk1, x, __cycle);
rustsfq_not NOT3 (x_d1, clk2, y, __cycle);
always @(posedge __cycle) begin
a_d1 <= a; b_d1 <= b; x_d1 <= x;
end
endmodule
module NorCombinational (a, b, clk, y, __cycle);
input a, b, clk, __cycle;
output y;
wire _BUFF3_q, _SPLIT1_q2, clk1, clk2, x;
rustsfq_split SPLIT1 (clk, clk1, _SPLIT1_q2, __cycle);
rustsfq_or OR2 (a, b, clk1, x, __cycle);
rustsfq_buff BUFF3 (_SPLIT1_q2, _BUFF3_q, __cycle);
rustsfq_buff BUFF4 (_BUFF3_q, clk2, __cycle);
rustsfq_not NOT5 (x, clk2, y, __cycle);
endmodule
module SingleCyclePath (a, clk, y, __cycle);
input a, clk, __cycle;
output y;
wire _AND4_q, a1, a2, clk1, clk2, x;
reg a1_d1 = 1'b0, a2_d1 = 1'b0, x_d1 = 1'b0;
rustsfq_split SPLIT1 (a, a1, a2, __cycle);
rustsfq_split SPLIT2 (clk, clk1, clk2, __cycle);
rustsfq_dff DFF3 (a1_d1, clk1, x, __cycle);
rustsfq_and AND4 (x_d1, a2_d1, clk2, _AND4_q, __cycle);
rustsfq_jtl JTL5 (_AND4_q, y, __cycle);
always @(posedge __cycle) begin
a2_d1 <= a2; x_d1 <= x; a1_d1 <= a1;
end
endmodule
module MultiCyclePath (a, clk, y, __cycle);
input a, clk, __cycle;
output y;
wire _AND38_q, _BUFF10_q, _BUFF11_q, _BUFF12_q, _BUFF13_q, _BUFF14_q, _BUFF15_q, _BUFF16_q, _BUFF17_q, _BUFF18_q, _BUFF19_q, _BUFF20_q, _BUFF21_q, _BUFF22_q, _BUFF23_q, _BUFF24_q, _BUFF25_q, _BUFF26_q, _BUFF27_q, _BUFF28_q, _BUFF29_q, _BUFF2_q, _BUFF30_q, _BUFF31_q, _BUFF32_q, _BUFF36_q, _BUFF3_q, _BUFF4_q, _BUFF5_q, _BUFF6_q, _BUFF7_q, _BUFF8_q, _BUFF9_q, _DFF35_q, a1, a2_end, a2_start, clk1, clk2, x;
reg a1_d1 = 1'b0, a2_end_d1 = 1'b0, a2_end_d2 = 1'b0, a2_end_d3 = 1'b0, x_d1 = 1'b0;
rustsfq_split SPLIT1 (a, a1, a2_start, __cycle);
rustsfq_buff BUFF2 (a2_start, _BUFF2_q, __cycle);
rustsfq_buff BUFF3 (_BUFF2_q, _BUFF3_q, __cycle);
rustsfq_buff BUFF4 (_BUFF3_q, _BUFF4_q, __cycle);
rustsfq_buff BUFF5 (_BUFF4_q, _BUFF5_q, __cycle);
rustsfq_buff BUFF6 (_BUFF5_q, _BUFF6_q, __cycle);
rustsfq_buff BUFF7 (_BUFF6_q, _BUFF7_q, __cycle);
rustsfq_buff BUFF8 (_BUFF7_q, _BUFF8_q, __cycle);
rustsfq_buff BUFF9 (_BUFF8_q, _BUFF9_q, __cycle);
rustsfq_buff BUFF10 (_BUFF9_q, _BUFF10_q, __cycle);
rustsfq_buff BUFF11 (_BUFF10_q, _BUFF11_q, __cycle);
rustsfq_buff BUFF12 (_BUFF11_q, _BUFF12_q, __cycle);
rustsfq_buff BUFF13 (_BUFF12_q, _BUFF13_q, __cycle);
rustsfq_buff BUFF14 (_BUFF13_q, _BUFF14_q, __cycle);
rustsfq_buff BUFF15 (_BUFF14_q, _BUFF15_q, __cycle);
rustsfq_buff BUFF16 (_BUFF15_q, _BUFF16_q, __cycle);
rustsfq_buff BUFF17 (_BUFF16_q, _BUFF17_q, __cycle);
rustsfq_buff BUFF18 (_BUFF17_q, _BUFF18_q, __cycle);
rustsfq_buff BUFF19 (_BUFF18_q, _BUFF19_q, __cycle);
rustsfq_buff BUFF20 (_BUFF19_q, _BUFF20_q, __cycle);
rustsfq_buff BUFF21 (_BUFF20_q, _BUFF21_q, __cycle);
rustsfq_buff BUFF22 (_BUFF21_q, _BUFF22_q, __cycle);
rustsfq_buff BUFF23 (_BUFF22_q, _BUFF23_q, __cycle);
rustsfq_buff BUFF24 (_BUFF23_q, _BUFF24_q, __cycle);
rustsfq_buff BUFF25 (_BUFF24_q, _BUFF25_q, __cycle);
rustsfq_buff BUFF26 (_BUFF25_q, _BUFF26_q, __cycle);
rustsfq_buff BUFF27 (_BUFF26_q, _BUFF27_q, __cycle);
rustsfq_buff BUFF28 (_BUFF27_q, _BUFF28_q, __cycle);
rustsfq_buff BUFF29 (_BUFF28_q, _BUFF29_q, __cycle);
rustsfq_buff BUFF30 (_BUFF29_q, _BUFF30_q, __cycle);
rustsfq_buff BUFF31 (_BUFF30_q, _BUFF31_q, __cycle);
rustsfq_buff BUFF32 (_BUFF31_q, _BUFF32_q, __cycle);
rustsfq_buff BUFF33 (_BUFF32_q, a2_end, __cycle);
rustsfq_split SPLIT34 (clk, clk1, clk2, __cycle);
rustsfq_dff DFF35 (a1_d1, clk1, _DFF35_q, __cycle);
rustsfq_buff BUFF36 (_DFF35_q, _BUFF36_q, __cycle);
rustsfq_buff BUFF37 (_BUFF36_q, x, __cycle);
rustsfq_and AND38 (x_d1, a2_end_d3, clk2, _AND38_q, __cycle);
rustsfq_jtl JTL39 (_AND38_q, y, __cycle);
always @(posedge __cycle) begin
a1_d1 <= a1; a2_end_d1 <= a2_end; a2_end_d2 <= a2_end_d1; a2_end_d3 <= a2_end_d2; x_d1 <= x;
end
endmodule
module ClockBetweenData (a, b, clk, y, __cycle);
input a, b, clk, __cycle;
output y;
wire _BUFF3_q, _BUFF4_q, _BUFF5_q, _BUFF6_q, _SPLIT1_q2, clk1, clk2, x, y0, y1;
reg y1_d1 = 1'b0;
rustsfq_split SPLIT1 (clk, clk1, _SPLIT1_q2, __cycle);
rustsfq_and AND2 (a, b, clk1, x, __cycle);
rustsfq_buff BUFF3 (_SPLIT1_q2, _BUFF3_q, __cycle);
rustsfq_buff BUFF4 (_BUFF3_q, _BUFF4_q, __cycle);
rustsfq_buff BUFF5 (_BUFF4_q, _BUFF5_q, __cycle);
rustsfq_buff BUFF6 (_BUFF5_q, _BUFF6_q, __cycle);
rustsfq_buff BUFF7 (_BUFF6_q, clk2, __cycle);
rustsfq_or OR8 (x, y1_d1, clk2, y0, __cycle);
rustsfq_split SPLIT9 (y0, y, y1, __cycle);
always @(posedge __cycle) begin
y1_d1 <= y1;
end
endmodule

samples/timings/logical/clock-between-test.sv
`include "all.v"
`include "modules.v"

module top;
  // Inputs
  reg a, b, clk;
  // Outputs
  wire y;

  reg __cycle;
  integer cycles;
  ClockBetweenData dut (.*);

  // Simulation cycles
  initial begin
    __cycle = 0;
    cycles  = 0;
    forever begin
      #1;
      __cycle = 0;
      #1;
      __cycle = 1;
      cycles  = cycles + 1;
    end
  end

  // Input patterns
  assign clk = 1;

  integer i;
  initial begin
    a = 0;
    b = 0;
    for (i = 0; i < 6; i++) begin
      @(posedge __cycle);
      a <= i[0];
      b <= i[1];
    end
    for (i = 0; i < 2; i++) begin
      @(posedge __cycle);
      a <= 0;
      b <= 0;
    end
    $finish;
  end

  initial begin
    $dumpfile("clock-between-test.vcd");
    $dumpvars(0, top);
  end
endmodule

samples/timings/logical/clock-between-test.vcd
$date
	Mon Jun 22 16:20:57 2026
$end
$version
	Icarus Verilog
$end
$timescale
	1s
$end
$scope module top $end
$var wire 1 ! clk $end
$var wire 1 " y $end
$var reg 1 # __cycle $end
$var reg 1 $ a $end
$var reg 1 % b $end
$var integer 32 & cycles [31:0] $end
$var integer 32 ' i [31:0] $end
$scope module dut $end
$var wire 1 # __cycle $end
$var wire 1 $ a $end
$var wire 1 % b $end
$var wire 1 ! clk $end
$var wire 1 ( y1 $end
$var wire 1 ) y0 $end
$var wire 1 " y $end
$var wire 1 * x $end
$var wire 1 + clk2 $end
$var wire 1 , clk1 $end
$var wire 1 - _SPLIT1_q2 $end
$var wire 1 . _BUFF6_q $end
$var wire 1 / _BUFF5_q $end
$var wire 1 0 _BUFF4_q $end
$var wire 1 1 _BUFF3_q $end
$var reg 1 2 y1_d1 $end
$scope module AND2 $end
$var wire 1 # __cycle $end
$var wire 1 $ a $end
$var wire 1 % b $end
$var wire 1 * q $end
$var wire 1 , clk $end
$var reg 1 3 a_reg $end
$var reg 1 4 b_reg $end
$upscope $end
$scope module BUFF3 $end
$var wire 1 # __cycle $end
$var wire 1 1 q $end
$var wire 1 - a $end
$upscope $end
$scope module BUFF4 $end
$var wire 1 # __cycle $end
$var wire 1 1 a $end
$var wire 1 0 q $end
$upscope $end
$scope module BUFF5 $end
$var wire 1 # __cycle $end
$var wire 1 0 a $end
$var wire 1 / q $end
$upscope $end
$scope module BUFF6 $end
$var wire 1 # __cycle $end
$var wire 1 / a $end
$var wire 1 . q $end
$upscope $end
$scope module BUFF7 $end
$var wire 1 # __cycle $end
$var wire 1 . a $end
$var wire 1 + q $end
$upscope $end
$scope module OR8 $end
$var wire 1 # __cycle $end
$var wire 1 * a $end
$var wire 1 2 b $end
$var wire 1 + clk $end
$var wire 1 ) q $end
$var reg 1 5 a_reg $end
$var reg 1 6 b_reg $end
$upscope $end
$scope module SPLIT1 $end
$var wire 1 # __cycle $end
$var wire 1 ! a $end
$var wire 1 , q1 $end
$var wire 1 - q2 $end
$upscope $end
$scope module SPLIT9 $end
$var wire 1 # __cycle $end
$var wire 1 ) a $end
$var wire 1 " q1 $end
$var wire 1 ( q2 $end
$upscope $end
$upscope $end
$upscope $end
$enddefinitions $end
$comment Show the parameter values. $end
$dumpall
$end
#0
$dumpvars
06
05
04
03
02
11
10
1/
1.
1-
1,
1+
0*
0)
0(
b0 '
b0 &
0%
0$
0#
0"
1!
$end
#2
b1 '
b1 &
1#
#3
0#
#4
1$
b10 '
b10 &
1#
#5
0#
#6
1%
0$
b11 '
b11 &
1#
#7
0#
#8
1"
1(
1)
1*
1$
b100 '
b100 &
1#
#9
0#
#10
0*
12
0%
0$
b101 '
b101 &
1#
#11
0#
#12
1$
b0 '
b110 &
1#
#13
0#
#14
0$
b1 '
b111 &
1#
#15
0#
#16
b10 '
b1000 &
1#
