lib/logical/all.v
`include "and.v"
`include "buff.v"
`include "dff.v"
`include "jtl.v"
`include "merge.v"
`include "ndro.sv"
`include "not.v"
`include "or.v"
`include "split.v"
`include "xnor.v"
`include "xor.v"
`include "zero_async.v"

lib/logical/not.v
module rustsfq_not (
    input  wire a,
    input  wire clk,
    output wire q,
    input  wire __cycle
);
  reg a_reg = 1'b0;

  assign q = clk ? ~(a | a_reg) : 1'b0;

  always @(posedge __cycle) begin
    if (clk) begin
      a_reg <= 1'b0;
    end else begin
      a_reg <= a | a_reg;
    end
  end
endmodule

lib/logical/or.v
module rustsfq_or (
    input  wire a,
    input  wire b,
    input  wire clk,
    output wire q,
    input  wire __cycle
);
  reg a_reg = 1'b0, b_reg = 1'b0;

  assign q = clk ? (a | a_reg) | (b | b_reg) : 1'b0;

  always @(posedge __cycle) begin
    if (clk) begin
      a_reg <= 1'b0;
      b_reg <= 1'b0;
    end else begin
      a_reg <= a | a_reg;
      b_reg <= b | b_reg;
    end
  end
endmodule

lib/logical/split.v
module rustsfq_split (
    input  wire a,
    output wire q1,
    output wire q2,
    input  wire __cycle
);
  assign q1 = a;
  assign q2 = a;
endmodule

samples/timings/logical/modules.v
module NorPipelined (a, b, clk, y, __cycle);
input a, b, clk, __cycle;
output y;
wire clk1, clk2, x;
reg a_d1 = 1'b0, b_d1 = 1'b0, x_d1 = 1'b0;
rustsfq_split SPLIT1 (clk, clk1, clk2, __cycle);
rustsfq_or OR2 (a_d1, b_d1, clk1, x, __cycle);
rustsfq_not NOT3 (x_d1, clk2, y, __cycle);
always @(posedge __cycle) begin
a_d1 <= a; b_d1 <= b; x_d1 <= x;
end
endmodule
module NorCombinational (a, b, clk, y, __cycle);
input a, b, clk, __cycle;
output y;
wire _BUFF3_q, _SPLIT1_q2, clk1, clk2, x;
rustsfq_split SPLIT1 (clk, clk1, _SPLIT1_q2, __cycle);
rustsfq_or OR2 (a, b, clk1, x, __cycle);
rustsfq_buff BUFF3 (_SPLIT1_q2, _BUFF3_q, __cycle);
rustsfq_buff BUFF4 (_BUFF3_q, clk2, __cycle);
rustsfq_not NOT5 (x, clk2, y, __cycle);
endmodule

samples/timings/logical/nor-p-test.sv
`include "all.v"
`include "modules.v"

module top;
  // Inputs
  reg a, b, clk;
  // Outputs
  wire y;

  reg __cycle;
  integer cycles;
  NorPipelined dut (.*);

  // Simulation cycles
  initial begin
    __cycle = 0;
    cycles  = 0;
    forever begin
      #1;
      __cycle = 0;
      #1;
      __cycle = 1;
      cycles  = cycles + 1;
    end
  end

  // Input patterns
  assign clk = 1;

  integer i;
  initial begin
    a = 0;
    b = 0;
    for (i = 0; i < 4; i++) begin
      @(posedge __cycle);
      {a, b} <= i;
    end
    for (i = 0; i < 3; i++) begin
      @(posedge __cycle);
      {a, b} <= 2'b00;
    end
    $finish;
  end

  initial begin
    $dumpfile("nor-p-test.vcd");
    $dumpvars(0, top);
  end
endmodule

samples/timings/logical/nor-p-test.vcd
$date
	Wed Jun 17 15:53:44 2026
$end
$version
	Icarus Verilog
$end
$timescale
	1s
$end
$scope module top $end
$var wire 1 ! clk $end
$var wire 1 " y $end
$var reg 1 # __cycle $end
$var reg 1 $ a $end
$var reg 1 % b $end
$var integer 32 & cycles [31:0] $end
$var integer 32 ' i [31:0] $end
$scope module dut $end
$var wire 1 # __cycle $end
$var wire 1 $ a $end
$var wire 1 % b $end
$var wire 1 ! clk $end
$var wire 1 " y $end
$var wire 1 ( x $end
$var wire 1 ) clk2 $end
$var wire 1 * clk1 $end
$var reg 1 + a_d1 $end
$var reg 1 , b_d1 $end
$var reg 1 - x_d1 $end
$scope module NOT3 $end
$var wire 1 # __cycle $end
$var wire 1 - a $end
$var wire 1 " q $end
$var wire 1 ) clk $end
$var reg 1 . a_reg $end
$upscope $end
$scope module OR2 $end
$var wire 1 # __cycle $end
$var wire 1 + a $end
$var wire 1 , b $end
$var wire 1 ( q $end
$var wire 1 * clk $end
$var reg 1 / a_reg $end
$var reg 1 0 b_reg $end
$upscope $end
$scope module SPLIT1 $end
$var wire 1 # __cycle $end
$var wire 1 ! a $end
$var wire 1 * q1 $end
$var wire 1 ) q2 $end
$upscope $end
$upscope $end
$upscope $end
$enddefinitions $end
$comment Show the parameter values. $end
$dumpall
$end
#0
$dumpvars
00
0/
0.
0-
0,
0+
1*
1)
0(
b0 '
b0 &
0%
0$
0#
1"
1!
$end
#2
b1 '
b1 &
1#
#3
0#
#4
1%
b10 '
b10 &
1#
#5
0#
#6
1(
1,
1$
0%
b11 '
b11 &
1#
#7
0#
#8
0"
1%
0,
1-
1+
b0 '
b100 &
1#
#9
0#
#10
1,
0$
0%
b1 '
b101 &
1#
#11
0#
#12
0(
0,
0+
b10 '
b110 &
1#
#13
0#
#14
1"
0-
b11 '
b111 &
1#
