lib/logical/all.v
`include "and.v"
`include "buff.v"
`include "dff.v"
`include "jtl.v"
`include "merge.v"
`include "ndro.sv"
`include "not.v"
`include "or.v"
`include "split.v"
`include "xnor.v"
`include "xor.v"
`include "zero_async.v"

lib/logical/and.v
module rustsfq_and (
    input  wire a,
    input  wire b,
    input  wire clk,
    output wire q,
    input  wire __cycle
);
  reg a_reg = 1'b0, b_reg = 1'b0;
  assign q = clk ? (a | a_reg) & (b | b_reg) : 1'b0;

  always @(posedge __cycle) begin
    if (clk) begin
      a_reg <= 1'b0;
      b_reg <= 1'b0;
    end else begin
      a_reg <= a | a_reg;
      b_reg <= b | b_reg;
    end
  end
endmodule

lib/logical/dff.v
module rustsfq_dff (
    input  wire a,
    input  wire clk,
    output wire q,
    input  wire __cycle
);
  reg a_reg = 1'b0;

  assign q = clk ? (a | a_reg) : 1'b0;

  always @(posedge __cycle) begin
    if (clk) begin
      a_reg <= 1'b0;
    end else begin
      a_reg <= a | a_reg;
    end
  end
endmodule

lib/logical/split.v
module rustsfq_split (
    input  wire a,
    output wire q1,
    output wire q2,
    input  wire __cycle
);
  assign q1 = a;
  assign q2 = a;
endmodule

samples/timings/logical/modules.v
module NorPipelined (a, b, clk, y, __cycle);
input a, b, clk, __cycle;
output y;
wire clk1, clk2, x;
reg a_d1 = 1'b0, b_d1 = 1'b0, x_d1 = 1'b0;
rustsfq_split SPLIT1 (clk, clk1, clk2, __cycle);
rustsfq_or OR2 (a_d1, b_d1, clk1, x, __cycle);
rustsfq_not NOT3 (x_d1, clk2, y, __cycle);
always @(posedge __cycle) begin
x_d1 <= x; b_d1 <= b; a_d1 <= a;
end
endmodule
module NorCombinational (a, b, clk, y, __cycle);
input a, b, clk, __cycle;
output y;
wire _BUFF3_q, _SPLIT1_q2, clk1, clk2, x;
rustsfq_split SPLIT1 (clk, clk1, _SPLIT1_q2, __cycle);
rustsfq_or OR2 (a, b, clk1, x, __cycle);
rustsfq_buff BUFF3 (_SPLIT1_q2, _BUFF3_q, __cycle);
rustsfq_buff BUFF4 (_BUFF3_q, clk2, __cycle);
rustsfq_not NOT5 (x, clk2, y, __cycle);
endmodule
module SingleCyclePath (a, clk, y, __cycle);
input a, clk, __cycle;
output y;
wire a1, a2, clk1, clk2, x;
reg a1_d1 = 1'b0, a2_d1 = 1'b0, x_d1 = 1'b0;
rustsfq_split SPLIT1 (a, a1, a2, __cycle);
rustsfq_split SPLIT2 (clk, clk1, clk2, __cycle);
rustsfq_dff DFF3 (a1_d1, clk1, x, __cycle);
rustsfq_and AND4 (x_d1, a2_d1, clk2, y, __cycle);
always @(posedge __cycle) begin
x_d1 <= x; a1_d1 <= a1; a2_d1 <= a2;
end
endmodule
module MultiCyclePath (a, clk, y, __cycle);
input a, clk, __cycle;
output y;
wire _BUFF10_q, _BUFF11_q, _BUFF12_q, _BUFF13_q, _BUFF14_q, _BUFF15_q, _BUFF16_q, _BUFF17_q, _BUFF18_q, _BUFF19_q, _BUFF20_q, _BUFF2_q, _BUFF3_q, _BUFF4_q, _BUFF5_q, _BUFF6_q, _BUFF7_q, _BUFF8_q, _BUFF9_q, a1, a2_end, a2_start, clk1, clk2, x;
reg a1_d1 = 1'b0, a2_end_d1 = 1'b0, a2_end_d2 = 1'b0, a2_end_d3 = 1'b0, x_d1 = 1'b0;
rustsfq_split SPLIT1 (a, a1, a2_start, __cycle);
rustsfq_buff BUFF2 (a2_start, _BUFF2_q, __cycle);
rustsfq_buff BUFF3 (_BUFF2_q, _BUFF3_q, __cycle);
rustsfq_buff BUFF4 (_BUFF3_q, _BUFF4_q, __cycle);
rustsfq_buff BUFF5 (_BUFF4_q, _BUFF5_q, __cycle);
rustsfq_buff BUFF6 (_BUFF5_q, _BUFF6_q, __cycle);
rustsfq_buff BUFF7 (_BUFF6_q, _BUFF7_q, __cycle);
rustsfq_buff BUFF8 (_BUFF7_q, _BUFF8_q, __cycle);
rustsfq_buff BUFF9 (_BUFF8_q, _BUFF9_q, __cycle);
rustsfq_buff BUFF10 (_BUFF9_q, _BUFF10_q, __cycle);
rustsfq_buff BUFF11 (_BUFF10_q, _BUFF11_q, __cycle);
rustsfq_buff BUFF12 (_BUFF11_q, _BUFF12_q, __cycle);
rustsfq_buff BUFF13 (_BUFF12_q, _BUFF13_q, __cycle);
rustsfq_buff BUFF14 (_BUFF13_q, _BUFF14_q, __cycle);
rustsfq_buff BUFF15 (_BUFF14_q, _BUFF15_q, __cycle);
rustsfq_buff BUFF16 (_BUFF15_q, _BUFF16_q, __cycle);
rustsfq_buff BUFF17 (_BUFF16_q, _BUFF17_q, __cycle);
rustsfq_buff BUFF18 (_BUFF17_q, _BUFF18_q, __cycle);
rustsfq_buff BUFF19 (_BUFF18_q, _BUFF19_q, __cycle);
rustsfq_buff BUFF20 (_BUFF19_q, _BUFF20_q, __cycle);
rustsfq_buff BUFF21 (_BUFF20_q, a2_end, __cycle);
rustsfq_split SPLIT22 (clk, clk1, clk2, __cycle);
rustsfq_dff DFF23 (a1_d1, clk1, x, __cycle);
rustsfq_and AND24 (x_d1, a2_end_d3, clk2, y, __cycle);
always @(posedge __cycle) begin
a1_d1 <= a1; x_d1 <= x; a2_end_d1 <= a2_end; a2_end_d2 <= a2_end_d1; a2_end_d3 <= a2_end_d2;
end
endmodule
module ClockBetweenData (a, b, clk, y, __cycle);
input a, b, clk, __cycle;
output y;
wire _OR3_q, clk1, clk2, x, y1;
reg a_d1 = 1'b0, b_d1 = 1'b0, y1_d1 = 1'b0;
rustsfq_split SPLIT1 (clk, clk1, clk2, __cycle);
rustsfq_and AND2 (a_d1, b_d1, clk1, x, __cycle);
rustsfq_or OR3 (x, y1_d1, clk2, _OR3_q, __cycle);
rustsfq_split SPLIT4 (_OR3_q, y, y1, __cycle);
always @(posedge __cycle) begin
a_d1 <= a; b_d1 <= b; y1_d1 <= y1;
end
endmodule

samples/timings/logical/single-cycle-test.sv
`include "all.v"
`include "modules.v"

module top;
  // Inputs
  reg a, clk;
  // Outputs
  wire y;

  reg __cycle;
  integer cycles;
  SingleCyclePath dut (.*);

  // Simulation cycles
  initial begin
    __cycle = 0;
    cycles  = 0;
    forever begin
      #1;
      __cycle = 0;
      #1;
      __cycle = 1;
      cycles  = cycles + 1;
    end
  end

  // Input patterns
  localparam N = 12;
  assign clk = 1;
  logic [N-1:0] patterns = 'b0110_1111_0000;

  integer i;
  initial begin
    a = 0;
    for (i = 0; i < N; i++) begin
      @(posedge __cycle);
      a <= patterns[N-1-i];
    end
    $finish;
  end

  initial begin
    $dumpfile("single-cycle-test.vcd");
    $dumpvars(0, top);
  end
endmodule

samples/timings/logical/single-cycle-test.vcd
$date
	Fri Jun 19 12:52:29 2026
$end
$version
	Icarus Verilog
$end
$timescale
	1s
$end
$scope module top $end
$var wire 1 ! clk $end
$var wire 1 " y $end
$var parameter 32 # N $end
$var reg 1 $ __cycle $end
$var reg 1 % a $end
$var reg 12 & patterns [11:0] $end
$var integer 32 ' cycles [31:0] $end
$var integer 32 ( i [31:0] $end
$scope module dut $end
$var wire 1 $ __cycle $end
$var wire 1 % a $end
$var wire 1 ! clk $end
$var wire 1 " y $end
$var wire 1 ) x $end
$var wire 1 * clk2 $end
$var wire 1 + clk1 $end
$var wire 1 , a2 $end
$var wire 1 - a1 $end
$var reg 1 . a1_d1 $end
$var reg 1 / a2_d1 $end
$var reg 1 0 x_d1 $end
$scope module AND4 $end
$var wire 1 $ __cycle $end
$var wire 1 0 a $end
$var wire 1 / b $end
$var wire 1 " q $end
$var wire 1 * clk $end
$var reg 1 1 a_reg $end
$var reg 1 2 b_reg $end
$upscope $end
$scope module DFF3 $end
$var wire 1 $ __cycle $end
$var wire 1 . a $end
$var wire 1 ) q $end
$var wire 1 + clk $end
$var reg 1 3 a_reg $end
$upscope $end
$scope module SPLIT1 $end
$var wire 1 $ __cycle $end
$var wire 1 % a $end
$var wire 1 - q1 $end
$var wire 1 , q2 $end
$upscope $end
$scope module SPLIT2 $end
$var wire 1 $ __cycle $end
$var wire 1 ! a $end
$var wire 1 + q1 $end
$var wire 1 * q2 $end
$upscope $end
$upscope $end
$upscope $end
$enddefinitions $end
$comment Show the parameter values. $end
$dumpall
b1100 #
$end
#0
$dumpvars
03
02
01
00
0/
0.
0-
0,
1+
1*
0)
b0 (
b0 '
b11011110000 &
0%
0$
0"
1!
$end
#2
b1 (
b1 '
1$
#3
0$
#4
1-
1,
1%
b10 (
b10 '
1$
#5
0$
#6
1)
1/
1.
b11 (
b11 '
1$
#7
0$
#8
1"
0-
0,
0%
10
b100 (
b100 '
1$
#9
0$
#10
0"
0)
0/
0.
1-
1,
1%
b101 (
b101 '
1$
#11
0$
#12
1)
1/
1.
00
b110 (
b110 '
1$
#13
0$
#14
1"
10
b111 (
b111 '
1$
#15
0$
#16
b1000 (
b1000 '
1$
#17
0$
#18
0-
0,
0%
b1001 (
b1001 '
1$
#19
0$
#20
0"
0)
0/
0.
b1010 (
b1010 '
1$
#21
0$
#22
00
b1011 (
b1011 '
1$
#23
0$
#24
b1100 (
b1100 '
1$
